setup.py
panda_black_test/__init__.py
panda_black_test.egg-info/PKG-INFO
panda_black_test.egg-info/SOURCES.txt
panda_black_test.egg-info/dependency_links.txt
panda_black_test.egg-info/entry_points.txt
panda_black_test.egg-info/requires.txt
panda_black_test.egg-info/top_level.txt