Metadata-Version: 1.0
Name: panda-black-test
Version: 1.1
Summary: test for panda_black
Home-page: http://www.baidu.com/
Author: panda_black
Author-email: xxx
License: Apache License 2.0
Platform: unix
Platform: linux
Classifier: Programming Language :: Python :: 2.6
Classifier: Programming Language :: Python :: 2.7
Classifier: Programming Language :: Python :: 3
Classifier: Programming Language :: Python :: 3.3
